{
  "required": true,
  "minVersion": "0.8",
  "package": "traben.entity_model_features.mixin",
  "compatibilityLevel": "JAVA_17",
  "mixins": [
    "CuboidAccessor",
    "accessor.AnimalModelAccessor",
    "accessor.LivingEntityRendererAccessor",
    "accessor.ModelPartAccessor"
  ],
  "client": [
    "MixinSimpleResourceReload",
    "accessor.BipedEntityModelAccessor",
    "accessor.QuadrupedEntityModelAccessor",
    "renderers.MixinLivingEntityRenderer",
    "renderers.features.MixinSheepWoolFeatureRenderer"
  ],
  "injectors": {
    "defaultRequire": 1
  }
}
